odoo10_addon_mgmtsystem_hazard-10.0.1.0.0.99.dev10-py3.8-nspkg.pth
odoo/addons/mgmtsystem_hazard/README.rst
odoo/addons/mgmtsystem_hazard/__init__.py
odoo/addons/mgmtsystem_hazard/__manifest__.py
odoo/addons/mgmtsystem_hazard/demo/mgmtsystem_hazard_hazard.xml
odoo/addons/mgmtsystem_hazard/demo/mgmtsystem_hazard_origin.xml
odoo/addons/mgmtsystem_hazard/demo/mgmtsystem_hazard_probability.xml
odoo/addons/mgmtsystem_hazard/demo/mgmtsystem_hazard_severity.xml
odoo/addons/mgmtsystem_hazard/demo/mgmtsystem_hazard_type.xml
odoo/addons/mgmtsystem_hazard/demo/mgmtsystem_hazard_usage.xml
odoo/addons/mgmtsystem_hazard/i18n/am.po
odoo/addons/mgmtsystem_hazard/i18n/ar.po
odoo/addons/mgmtsystem_hazard/i18n/bg.po
odoo/addons/mgmtsystem_hazard/i18n/bs.po
odoo/addons/mgmtsystem_hazard/i18n/ca.po
odoo/addons/mgmtsystem_hazard/i18n/ca_ES.po
odoo/addons/mgmtsystem_hazard/i18n/cs.po
odoo/addons/mgmtsystem_hazard/i18n/da.po
odoo/addons/mgmtsystem_hazard/i18n/de.po
odoo/addons/mgmtsystem_hazard/i18n/el_GR.po
odoo/addons/mgmtsystem_hazard/i18n/en.po
odoo/addons/mgmtsystem_hazard/i18n/en_GB.po
odoo/addons/mgmtsystem_hazard/i18n/es.po
odoo/addons/mgmtsystem_hazard/i18n/es_AR.po
odoo/addons/mgmtsystem_hazard/i18n/es_CL.po
odoo/addons/mgmtsystem_hazard/i18n/es_CO.po
odoo/addons/mgmtsystem_hazard/i18n/es_CR.po
odoo/addons/mgmtsystem_hazard/i18n/es_DO.po
odoo/addons/mgmtsystem_hazard/i18n/es_EC.po
odoo/addons/mgmtsystem_hazard/i18n/es_ES.po
odoo/addons/mgmtsystem_hazard/i18n/es_MX.po
odoo/addons/mgmtsystem_hazard/i18n/es_PE.po
odoo/addons/mgmtsystem_hazard/i18n/es_PY.po
odoo/addons/mgmtsystem_hazard/i18n/es_VE.po
odoo/addons/mgmtsystem_hazard/i18n/et.po
odoo/addons/mgmtsystem_hazard/i18n/eu.po
odoo/addons/mgmtsystem_hazard/i18n/fa.po
odoo/addons/mgmtsystem_hazard/i18n/fi.po
odoo/addons/mgmtsystem_hazard/i18n/fr.po
odoo/addons/mgmtsystem_hazard/i18n/fr_CA.po
odoo/addons/mgmtsystem_hazard/i18n/fr_CH.po
odoo/addons/mgmtsystem_hazard/i18n/fr_FR.po
odoo/addons/mgmtsystem_hazard/i18n/gl.po
odoo10_addon_mgmtsystem_hazard-10.0.1.0.0.99.dev10.dist-info/METADATA
odoo10_addon_mgmtsystem_hazard-10.0.1.0.0.99.dev10.dist-info/WHEEL
odoo10_addon_mgmtsystem_hazard-10.0.1.0.0.99.dev10.dist-info/namespace_packages.txt
odoo10_addon_mgmtsystem_hazard-10.0.1.0.0.99.dev10.dist-info/top_level.txt
odoo10_addon_mgmtsystem_hazard-10.0.1.0.0.99.dev10.dist-info/RECORD
